sgearnbot/__init__.py
sgearnbot/lsedb.py
sgearnbot/sgearnbot.py
sgearnbot-1.0.0.dist-info/LICENSE
sgearnbot-1.0.0.dist-info/METADATA
sgearnbot-1.0.0.dist-info/WHEEL
sgearnbot-1.0.0.dist-info/top_level.txt
sgearnbot-1.0.0.dist-info/RECORD
