Metadata-Version: 2.1
Name: sgearnbot
Version: 1.0.0
Summary: help lib for Telegram bot
Author-email: HellHour <mahmoudookk6@gmail.com>
Project-URL: Homepage, https://github.com/LSEGITHUB/sgearnbot
Project-URL: Bug Tracker, https://github.com/LSEGITHUB/sgearnbot
Classifier: Programming Language :: Python :: 3
Classifier: License :: OSI Approved :: MIT License
Classifier: Operating System :: OS Independent
Requires-Python: >=3.7
License-File: LICENSE
